LICENSE.txt
MANIFEST.in
README.rst
setup.cfg
setup.py
data/data_file
wesky/__init__.py
wesky.egg-info/PKG-INFO
wesky.egg-info/SOURCES.txt
wesky.egg-info/dependency_links.txt
wesky.egg-info/entry_points.txt
wesky.egg-info/requires.txt
wesky.egg-info/top_level.txt