Metadata-Version: 1.1
Name: wesky
Version: 1.2.0
Summary: WeSkySoft
Home-page: https://github.com/sigai/LearnPython2017
Author: sigai
Author-email: vipfts@qq.com
License: MIT
Keywords: wesky
Platform: UNKNOWN
Classifier: Development Status :: 3 - Alpha
Classifier: Intended Audience :: Developers
Classifier: Topic :: Software Development :: Build Tools
Classifier: License :: OSI Approved :: MIT License
Classifier: Programming Language :: Python :: 3.6
